hrisapi/__init__.py
hrisapi/exception.py
hrisapi/schema.py
hrisapi/zoho_schema.py
hrisapi-0.0.2.dist-info/LICENSE
hrisapi-0.0.2.dist-info/METADATA
hrisapi-0.0.2.dist-info/WHEEL
hrisapi-0.0.2.dist-info/entry_points.txt
hrisapi-0.0.2.dist-info/top_level.txt
hrisapi-0.0.2.dist-info/RECORD
