Metadata-Version: 2.1
Name: hrisapi
Version: 0.0.2
Summary: Human Resource Information Systems API
Home-page: https://github.com/deep-compute/hrisapi
Author: deep-compute
Author-email: contact@deepcompute.com
License: UNKNOWN
Keywords: hris,hrisapi,hrms
Platform: UNKNOWN
Classifier: Environment :: Console
Classifier: Intended Audience :: Developers
Classifier: Natural Language :: English
Classifier: Programming Language :: Python
Classifier: Programming Language :: Python :: 3
Classifier: Programming Language :: Python :: 3.5
Classifier: License :: OSI Approved :: MIT License
Classifier: Operating System :: OS Independent
Requires-Dist: basescript (==0.2.8)
Requires-Dist: graphene (==2.1.3)
Requires-Dist: tornadoql (>=0.1.7)
Requires-Dist: requests (==2.21.0)
Requires-Dist: deeputil (==0.2.5)
Requires-Dist: timezonefinder (==4.0.2)
Requires-Dist: geopy (==1.19.0)
Requires-Dist: PyMemoize (==1.0.3)
Requires-Dist: redis (==3.2.1)
